pqc_hero/__init__.py
pqc_hero/pqc_hero.py
pqc_hero/engine/pqc_wrapper_shim.py
pqc_hero/engine/reports/audit_generator.py
pqc_hero/engine/reports/visual_diff.py
pqc_hero/engine/simulations/threat_actor.py
pqc_hero/engine/transformers/crypto_transformer.py
pqc_hero/engine/transformers/dependency_manager.py
pqc_hero/engine/transformers/import_manager.py
pqc_hero-0.1.0.dist-info/METADATA
pqc_hero-0.1.0.dist-info/WHEEL
pqc_hero-0.1.0.dist-info/entry_points.txt
pqc_hero-0.1.0.dist-info/top_level.txt
pqc_hero-0.1.0.dist-info/RECORD
