Metadata-Version: 2.4
Name: pqc-hero
Version: 0.1.0
Summary: Automated Post-Quantum Cryptography (PQC) remediation tool.
Requires-Python: >=3.8
Requires-Dist: typer[all]
Requires-Dist: rich
Requires-Dist: libcst
